baisou.py
baisou-1.0.9.dist-info/METADATA
baisou-1.0.9.dist-info/WHEEL
baisou-1.0.9.dist-info/entry_points.txt
baisou-1.0.9.dist-info/top_level.txt
baisou-1.0.9.dist-info/RECORD
