Metadata-Version: 2.1
Name: baisou
Version: 1.0.9
Summary: The Baidu Searcher On Python|Python 百度搜索工具
Home-page: UNKNOWN
Author: Python学霸
Author-email: python@xueba.com
License: UNKNOWN
Platform: UNKNOWN
Requires-Dist: requests
